<data>
  <mzm.gsp.ballbattle.confbean.SBallBattleLevelRawCfg id="965100000" maxLevel="5">
    <modelIds>
      <int>700301237</int>
      <int>700301237</int>
      <int>700301237</int>
      <int>700301237</int>
      <int>700301237</int>
      <int>0</int>
      <int>0</int>
      <int>0</int>
      <int>0</int>
      <int>0</int>
    </modelIds>
    <modelRatios>
      <int>40</int>
      <int>80</int>
      <int>120</int>
      <int>165</int>
      <int>205</int>
      <int>0</int>
      <int>0</int>
      <int>0</int>
      <int>0</int>
      <int>0</int>
    </modelRatios>
    <speedOffsets>
      <int>0</int>
      <int>-10</int>
      <int>-20</int>
      <int>-30</int>
      <int>-35</int>
      <int>0</int>
      <int>0</int>
      <int>0</int>
      <int>0</int>
      <int>0</int>
    </speedOffsets>
    <radii>
      <int>20</int>
      <int>38</int>
      <int>58</int>
      <int>71</int>
      <int>96</int>
      <int>0</int>
      <int>0</int>
      <int>0</int>
      <int>0</int>
      <int>0</int>
    </radii>
    <providedScores>
      <int>1</int>
      <int>2</int>
      <int>3</int>
      <int>4</int>
      <int>5</int>
      <int>0</int>
      <int>0</int>
      <int>0</int>
      <int>0</int>
      <int>0</int>
    </providedScores>
    <providedGenes>
      <int>2</int>
      <int>4</int>
      <int>6</int>
      <int>8</int>
      <int>10</int>
      <int>0</int>
      <int>0</int>
      <int>0</int>
      <int>0</int>
      <int>0</int>
    </providedGenes>
    <requiredGenes>
      <int>2</int>
      <int>4</int>
      <int>6</int>
      <int>8</int>
      <int>10</int>
      <int>0</int>
      <int>0</int>
      <int>0</int>
      <int>0</int>
      <int>0</int>
    </requiredGenes>
  </mzm.gsp.ballbattle.confbean.SBallBattleLevelRawCfg>
</data>
