<data>
  <mzm.gsp.luckystar.confbean.SLuckyStarGiftCfg recommend_user_group_id="1">
    <gift_list>
      <int>290500000</int>
    </gift_list>
  </mzm.gsp.luckystar.confbean.SLuckyStarGiftCfg>
  <mzm.gsp.luckystar.confbean.SLuckyStarGiftCfg recommend_user_group_id="2201">
    <gift_list>
      <int>290502201</int>
    </gift_list>
  </mzm.gsp.luckystar.confbean.SLuckyStarGiftCfg>
  <mzm.gsp.luckystar.confbean.SLuckyStarGiftCfg recommend_user_group_id="2">
    <gift_list>
      <int>290500001</int>
    </gift_list>
  </mzm.gsp.luckystar.confbean.SLuckyStarGiftCfg>
  <mzm.gsp.luckystar.confbean.SLuckyStarGiftCfg recommend_user_group_id="2202">
    <gift_list>
      <int>290502202</int>
    </gift_list>
  </mzm.gsp.luckystar.confbean.SLuckyStarGiftCfg>
  <mzm.gsp.luckystar.confbean.SLuckyStarGiftCfg recommend_user_group_id="3">
    <gift_list>
      <int>290500002</int>
    </gift_list>
  </mzm.gsp.luckystar.confbean.SLuckyStarGiftCfg>
  <mzm.gsp.luckystar.confbean.SLuckyStarGiftCfg recommend_user_group_id="2203">
    <gift_list>
      <int>290502203</int>
    </gift_list>
  </mzm.gsp.luckystar.confbean.SLuckyStarGiftCfg>
  <mzm.gsp.luckystar.confbean.SLuckyStarGiftCfg recommend_user_group_id="4">
    <gift_list>
      <int>290500003</int>
    </gift_list>
  </mzm.gsp.luckystar.confbean.SLuckyStarGiftCfg>
  <mzm.gsp.luckystar.confbean.SLuckyStarGiftCfg recommend_user_group_id="2204">
    <gift_list>
      <int>290502204</int>
    </gift_list>
  </mzm.gsp.luckystar.confbean.SLuckyStarGiftCfg>
  <mzm.gsp.luckystar.confbean.SLuckyStarGiftCfg recommend_user_group_id="5">
    <gift_list>
      <int>290500004</int>
    </gift_list>
  </mzm.gsp.luckystar.confbean.SLuckyStarGiftCfg>
  <mzm.gsp.luckystar.confbean.SLuckyStarGiftCfg recommend_user_group_id="2205">
    <gift_list>
      <int>290502205</int>
    </gift_list>
  </mzm.gsp.luckystar.confbean.SLuckyStarGiftCfg>
  <mzm.gsp.luckystar.confbean.SLuckyStarGiftCfg recommend_user_group_id="6">
    <gift_list>
      <int>290500005</int>
    </gift_list>
  </mzm.gsp.luckystar.confbean.SLuckyStarGiftCfg>
  <mzm.gsp.luckystar.confbean.SLuckyStarGiftCfg recommend_user_group_id="2206">
    <gift_list>
      <int>290502206</int>
    </gift_list>
  </mzm.gsp.luckystar.confbean.SLuckyStarGiftCfg>
  <mzm.gsp.luckystar.confbean.SLuckyStarGiftCfg recommend_user_group_id="7">
    <gift_list>
      <int>290500006</int>
    </gift_list>
  </mzm.gsp.luckystar.confbean.SLuckyStarGiftCfg>
  <mzm.gsp.luckystar.confbean.SLuckyStarGiftCfg recommend_user_group_id="8">
    <gift_list>
      <int>290500007</int>
    </gift_list>
  </mzm.gsp.luckystar.confbean.SLuckyStarGiftCfg>
  <mzm.gsp.luckystar.confbean.SLuckyStarGiftCfg recommend_user_group_id="9">
    <gift_list>
      <int>290500008</int>
    </gift_list>
  </mzm.gsp.luckystar.confbean.SLuckyStarGiftCfg>
  <mzm.gsp.luckystar.confbean.SLuckyStarGiftCfg recommend_user_group_id="10">
    <gift_list>
      <int>290500009</int>
    </gift_list>
  </mzm.gsp.luckystar.confbean.SLuckyStarGiftCfg>
  <mzm.gsp.luckystar.confbean.SLuckyStarGiftCfg recommend_user_group_id="11">
    <gift_list>
      <int>290500010</int>
    </gift_list>
  </mzm.gsp.luckystar.confbean.SLuckyStarGiftCfg>
  <mzm.gsp.luckystar.confbean.SLuckyStarGiftCfg recommend_user_group_id="12">
    <gift_list>
      <int>290500011</int>
    </gift_list>
  </mzm.gsp.luckystar.confbean.SLuckyStarGiftCfg>
  <mzm.gsp.luckystar.confbean.SLuckyStarGiftCfg recommend_user_group_id="13">
    <gift_list>
      <int>290500012</int>
    </gift_list>
  </mzm.gsp.luckystar.confbean.SLuckyStarGiftCfg>
  <mzm.gsp.luckystar.confbean.SLuckyStarGiftCfg recommend_user_group_id="14">
    <gift_list>
      <int>290500013</int>
    </gift_list>
  </mzm.gsp.luckystar.confbean.SLuckyStarGiftCfg>
  <mzm.gsp.luckystar.confbean.SLuckyStarGiftCfg recommend_user_group_id="15">
    <gift_list>
      <int>290500014</int>
    </gift_list>
  </mzm.gsp.luckystar.confbean.SLuckyStarGiftCfg>
  <mzm.gsp.luckystar.confbean.SLuckyStarGiftCfg recommend_user_group_id="17">
    <gift_list>
      <int>290500016</int>
    </gift_list>
  </mzm.gsp.luckystar.confbean.SLuckyStarGiftCfg>
  <mzm.gsp.luckystar.confbean.SLuckyStarGiftCfg recommend_user_group_id="16">
    <gift_list>
      <int>290500015</int>
    </gift_list>
  </mzm.gsp.luckystar.confbean.SLuckyStarGiftCfg>
  <mzm.gsp.luckystar.confbean.SLuckyStarGiftCfg recommend_user_group_id="19">
    <gift_list>
      <int>290500018</int>
    </gift_list>
  </mzm.gsp.luckystar.confbean.SLuckyStarGiftCfg>
  <mzm.gsp.luckystar.confbean.SLuckyStarGiftCfg recommend_user_group_id="18">
    <gift_list>
      <int>290500017</int>
    </gift_list>
  </mzm.gsp.luckystar.confbean.SLuckyStarGiftCfg>
  <mzm.gsp.luckystar.confbean.SLuckyStarGiftCfg recommend_user_group_id="21">
    <gift_list>
      <int>290500020</int>
    </gift_list>
  </mzm.gsp.luckystar.confbean.SLuckyStarGiftCfg>
  <mzm.gsp.luckystar.confbean.SLuckyStarGiftCfg recommend_user_group_id="20">
    <gift_list>
      <int>290500019</int>
    </gift_list>
  </mzm.gsp.luckystar.confbean.SLuckyStarGiftCfg>
  <mzm.gsp.luckystar.confbean.SLuckyStarGiftCfg recommend_user_group_id="23">
    <gift_list>
      <int>290500022</int>
    </gift_list>
  </mzm.gsp.luckystar.confbean.SLuckyStarGiftCfg>
  <mzm.gsp.luckystar.confbean.SLuckyStarGiftCfg recommend_user_group_id="22">
    <gift_list>
      <int>290500021</int>
    </gift_list>
  </mzm.gsp.luckystar.confbean.SLuckyStarGiftCfg>
  <mzm.gsp.luckystar.confbean.SLuckyStarGiftCfg recommend_user_group_id="24">
    <gift_list>
      <int>290500023</int>
    </gift_list>
  </mzm.gsp.luckystar.confbean.SLuckyStarGiftCfg>
  <mzm.gsp.luckystar.confbean.SLuckyStarGiftCfg recommend_user_group_id="2708">
    <gift_list>
      <int>290502708</int>
    </gift_list>
  </mzm.gsp.luckystar.confbean.SLuckyStarGiftCfg>
  <mzm.gsp.luckystar.confbean.SLuckyStarGiftCfg recommend_user_group_id="2704">
    <gift_list>
      <int>290502704</int>
    </gift_list>
  </mzm.gsp.luckystar.confbean.SLuckyStarGiftCfg>
  <mzm.gsp.luckystar.confbean.SLuckyStarGiftCfg recommend_user_group_id="2705">
    <gift_list>
      <int>290502705</int>
    </gift_list>
  </mzm.gsp.luckystar.confbean.SLuckyStarGiftCfg>
  <mzm.gsp.luckystar.confbean.SLuckyStarGiftCfg recommend_user_group_id="2706">
    <gift_list>
      <int>290502706</int>
    </gift_list>
  </mzm.gsp.luckystar.confbean.SLuckyStarGiftCfg>
  <mzm.gsp.luckystar.confbean.SLuckyStarGiftCfg recommend_user_group_id="2707">
    <gift_list>
      <int>290502707</int>
    </gift_list>
  </mzm.gsp.luckystar.confbean.SLuckyStarGiftCfg>
  <mzm.gsp.luckystar.confbean.SLuckyStarGiftCfg recommend_user_group_id="2701">
    <gift_list>
      <int>290502701</int>
    </gift_list>
  </mzm.gsp.luckystar.confbean.SLuckyStarGiftCfg>
  <mzm.gsp.luckystar.confbean.SLuckyStarGiftCfg recommend_user_group_id="2703">
    <gift_list>
      <int>290502703</int>
    </gift_list>
  </mzm.gsp.luckystar.confbean.SLuckyStarGiftCfg>
  <mzm.gsp.luckystar.confbean.SLuckyStarGiftCfg recommend_user_group_id="2702">
    <gift_list>
      <int>290502702</int>
    </gift_list>
  </mzm.gsp.luckystar.confbean.SLuckyStarGiftCfg>
  <mzm.gsp.luckystar.confbean.SLuckyStarGiftCfg recommend_user_group_id="2511">
    <gift_list>
      <int>290502511</int>
    </gift_list>
  </mzm.gsp.luckystar.confbean.SLuckyStarGiftCfg>
  <mzm.gsp.luckystar.confbean.SLuckyStarGiftCfg recommend_user_group_id="2810">
    <gift_list>
      <int>290502810</int>
    </gift_list>
  </mzm.gsp.luckystar.confbean.SLuckyStarGiftCfg>
  <mzm.gsp.luckystar.confbean.SLuckyStarGiftCfg recommend_user_group_id="2510">
    <gift_list>
      <int>290502510</int>
    </gift_list>
  </mzm.gsp.luckystar.confbean.SLuckyStarGiftCfg>
  <mzm.gsp.luckystar.confbean.SLuckyStarGiftCfg recommend_user_group_id="2811">
    <gift_list>
      <int>290502811</int>
    </gift_list>
  </mzm.gsp.luckystar.confbean.SLuckyStarGiftCfg>
  <mzm.gsp.luckystar.confbean.SLuckyStarGiftCfg recommend_user_group_id="2509">
    <gift_list>
      <int>290502509</int>
    </gift_list>
  </mzm.gsp.luckystar.confbean.SLuckyStarGiftCfg>
  <mzm.gsp.luckystar.confbean.SLuckyStarGiftCfg recommend_user_group_id="2808">
    <gift_list>
      <int>290502808</int>
    </gift_list>
  </mzm.gsp.luckystar.confbean.SLuckyStarGiftCfg>
  <mzm.gsp.luckystar.confbean.SLuckyStarGiftCfg recommend_user_group_id="2508">
    <gift_list>
      <int>290502508</int>
    </gift_list>
  </mzm.gsp.luckystar.confbean.SLuckyStarGiftCfg>
  <mzm.gsp.luckystar.confbean.SLuckyStarGiftCfg recommend_user_group_id="2809">
    <gift_list>
      <int>290502809</int>
    </gift_list>
  </mzm.gsp.luckystar.confbean.SLuckyStarGiftCfg>
  <mzm.gsp.luckystar.confbean.SLuckyStarGiftCfg recommend_user_group_id="2507">
    <gift_list>
      <int>290502507</int>
    </gift_list>
  </mzm.gsp.luckystar.confbean.SLuckyStarGiftCfg>
  <mzm.gsp.luckystar.confbean.SLuckyStarGiftCfg recommend_user_group_id="2814">
    <gift_list>
      <int>290502814</int>
    </gift_list>
  </mzm.gsp.luckystar.confbean.SLuckyStarGiftCfg>
  <mzm.gsp.luckystar.confbean.SLuckyStarGiftCfg recommend_user_group_id="2506">
    <gift_list>
      <int>290502506</int>
    </gift_list>
  </mzm.gsp.luckystar.confbean.SLuckyStarGiftCfg>
  <mzm.gsp.luckystar.confbean.SLuckyStarGiftCfg recommend_user_group_id="2815">
    <gift_list>
      <int>290502815</int>
    </gift_list>
  </mzm.gsp.luckystar.confbean.SLuckyStarGiftCfg>
  <mzm.gsp.luckystar.confbean.SLuckyStarGiftCfg recommend_user_group_id="2505">
    <gift_list>
      <int>290502505</int>
    </gift_list>
  </mzm.gsp.luckystar.confbean.SLuckyStarGiftCfg>
  <mzm.gsp.luckystar.confbean.SLuckyStarGiftCfg recommend_user_group_id="2812">
    <gift_list>
      <int>290502812</int>
    </gift_list>
  </mzm.gsp.luckystar.confbean.SLuckyStarGiftCfg>
  <mzm.gsp.luckystar.confbean.SLuckyStarGiftCfg recommend_user_group_id="2504">
    <gift_list>
      <int>290502504</int>
    </gift_list>
  </mzm.gsp.luckystar.confbean.SLuckyStarGiftCfg>
  <mzm.gsp.luckystar.confbean.SLuckyStarGiftCfg recommend_user_group_id="2813">
    <gift_list>
      <int>290502813</int>
    </gift_list>
  </mzm.gsp.luckystar.confbean.SLuckyStarGiftCfg>
  <mzm.gsp.luckystar.confbean.SLuckyStarGiftCfg recommend_user_group_id="2503">
    <gift_list>
      <int>290502503</int>
    </gift_list>
  </mzm.gsp.luckystar.confbean.SLuckyStarGiftCfg>
  <mzm.gsp.luckystar.confbean.SLuckyStarGiftCfg recommend_user_group_id="2802">
    <gift_list>
      <int>290502802</int>
    </gift_list>
  </mzm.gsp.luckystar.confbean.SLuckyStarGiftCfg>
  <mzm.gsp.luckystar.confbean.SLuckyStarGiftCfg recommend_user_group_id="2502">
    <gift_list>
      <int>290502502</int>
    </gift_list>
  </mzm.gsp.luckystar.confbean.SLuckyStarGiftCfg>
  <mzm.gsp.luckystar.confbean.SLuckyStarGiftCfg recommend_user_group_id="2803">
    <gift_list>
      <int>290502803</int>
    </gift_list>
  </mzm.gsp.luckystar.confbean.SLuckyStarGiftCfg>
  <mzm.gsp.luckystar.confbean.SLuckyStarGiftCfg recommend_user_group_id="2501">
    <gift_list>
      <int>290502501</int>
    </gift_list>
  </mzm.gsp.luckystar.confbean.SLuckyStarGiftCfg>
  <mzm.gsp.luckystar.confbean.SLuckyStarGiftCfg recommend_user_group_id="2801">
    <gift_list>
      <int>290502801</int>
    </gift_list>
  </mzm.gsp.luckystar.confbean.SLuckyStarGiftCfg>
  <mzm.gsp.luckystar.confbean.SLuckyStarGiftCfg recommend_user_group_id="2806">
    <gift_list>
      <int>290502806</int>
    </gift_list>
  </mzm.gsp.luckystar.confbean.SLuckyStarGiftCfg>
  <mzm.gsp.luckystar.confbean.SLuckyStarGiftCfg recommend_user_group_id="2807">
    <gift_list>
      <int>290502807</int>
    </gift_list>
  </mzm.gsp.luckystar.confbean.SLuckyStarGiftCfg>
  <mzm.gsp.luckystar.confbean.SLuckyStarGiftCfg recommend_user_group_id="2804">
    <gift_list>
      <int>290502804</int>
    </gift_list>
  </mzm.gsp.luckystar.confbean.SLuckyStarGiftCfg>
  <mzm.gsp.luckystar.confbean.SLuckyStarGiftCfg recommend_user_group_id="2805">
    <gift_list>
      <int>290502805</int>
    </gift_list>
  </mzm.gsp.luckystar.confbean.SLuckyStarGiftCfg>
  <mzm.gsp.luckystar.confbean.SLuckyStarGiftCfg recommend_user_group_id="2516">
    <gift_list>
      <int>290502516</int>
    </gift_list>
  </mzm.gsp.luckystar.confbean.SLuckyStarGiftCfg>
  <mzm.gsp.luckystar.confbean.SLuckyStarGiftCfg recommend_user_group_id="2514">
    <gift_list>
      <int>290502514</int>
    </gift_list>
  </mzm.gsp.luckystar.confbean.SLuckyStarGiftCfg>
  <mzm.gsp.luckystar.confbean.SLuckyStarGiftCfg recommend_user_group_id="2515">
    <gift_list>
      <int>290502515</int>
    </gift_list>
  </mzm.gsp.luckystar.confbean.SLuckyStarGiftCfg>
  <mzm.gsp.luckystar.confbean.SLuckyStarGiftCfg recommend_user_group_id="2512">
    <gift_list>
      <int>290502512</int>
    </gift_list>
  </mzm.gsp.luckystar.confbean.SLuckyStarGiftCfg>
  <mzm.gsp.luckystar.confbean.SLuckyStarGiftCfg recommend_user_group_id="2513">
    <gift_list>
      <int>290502513</int>
    </gift_list>
  </mzm.gsp.luckystar.confbean.SLuckyStarGiftCfg>
  <mzm.gsp.luckystar.confbean.SLuckyStarGiftCfg recommend_user_group_id="2302">
    <gift_list>
      <int>290502302</int>
    </gift_list>
  </mzm.gsp.luckystar.confbean.SLuckyStarGiftCfg>
  <mzm.gsp.luckystar.confbean.SLuckyStarGiftCfg recommend_user_group_id="2303">
    <gift_list>
      <int>290502303</int>
    </gift_list>
  </mzm.gsp.luckystar.confbean.SLuckyStarGiftCfg>
  <mzm.gsp.luckystar.confbean.SLuckyStarGiftCfg recommend_user_group_id="2301">
    <gift_list>
      <int>290502301</int>
    </gift_list>
  </mzm.gsp.luckystar.confbean.SLuckyStarGiftCfg>
  <mzm.gsp.luckystar.confbean.SLuckyStarGiftCfg recommend_user_group_id="2306">
    <gift_list>
      <int>290502306</int>
    </gift_list>
  </mzm.gsp.luckystar.confbean.SLuckyStarGiftCfg>
  <mzm.gsp.luckystar.confbean.SLuckyStarGiftCfg recommend_user_group_id="2307">
    <gift_list>
      <int>290502307</int>
    </gift_list>
  </mzm.gsp.luckystar.confbean.SLuckyStarGiftCfg>
  <mzm.gsp.luckystar.confbean.SLuckyStarGiftCfg recommend_user_group_id="2304">
    <gift_list>
      <int>290502304</int>
    </gift_list>
  </mzm.gsp.luckystar.confbean.SLuckyStarGiftCfg>
  <mzm.gsp.luckystar.confbean.SLuckyStarGiftCfg recommend_user_group_id="8009">
    <gift_list>
      <int>290508059</int>
      <int>290508058</int>
      <int>290508057</int>
      <int>290508056</int>
      <int>290508055</int>
      <int>290508054</int>
    </gift_list>
  </mzm.gsp.luckystar.confbean.SLuckyStarGiftCfg>
  <mzm.gsp.luckystar.confbean.SLuckyStarGiftCfg recommend_user_group_id="2305">
    <gift_list>
      <int>290502305</int>
    </gift_list>
  </mzm.gsp.luckystar.confbean.SLuckyStarGiftCfg>
  <mzm.gsp.luckystar.confbean.SLuckyStarGiftCfg recommend_user_group_id="8008">
    <gift_list>
      <int>290508050</int>
      <int>290508053</int>
      <int>290508051</int>
      <int>290508052</int>
      <int>290508048</int>
      <int>290508049</int>
    </gift_list>
  </mzm.gsp.luckystar.confbean.SLuckyStarGiftCfg>
  <mzm.gsp.luckystar.confbean.SLuckyStarGiftCfg recommend_user_group_id="2310">
    <gift_list>
      <int>290502310</int>
    </gift_list>
  </mzm.gsp.luckystar.confbean.SLuckyStarGiftCfg>
  <mzm.gsp.luckystar.confbean.SLuckyStarGiftCfg recommend_user_group_id="2311">
    <gift_list>
      <int>290502311</int>
    </gift_list>
  </mzm.gsp.luckystar.confbean.SLuckyStarGiftCfg>
  <mzm.gsp.luckystar.confbean.SLuckyStarGiftCfg recommend_user_group_id="2308">
    <gift_list>
      <int>290502308</int>
    </gift_list>
  </mzm.gsp.luckystar.confbean.SLuckyStarGiftCfg>
  <mzm.gsp.luckystar.confbean.SLuckyStarGiftCfg recommend_user_group_id="2309">
    <gift_list>
      <int>290502309</int>
    </gift_list>
  </mzm.gsp.luckystar.confbean.SLuckyStarGiftCfg>
  <mzm.gsp.luckystar.confbean.SLuckyStarGiftCfg recommend_user_group_id="2314">
    <gift_list>
      <int>290502314</int>
    </gift_list>
  </mzm.gsp.luckystar.confbean.SLuckyStarGiftCfg>
  <mzm.gsp.luckystar.confbean.SLuckyStarGiftCfg recommend_user_group_id="8003">
    <gift_list>
      <int>290508022</int>
      <int>290508023</int>
      <int>290508020</int>
      <int>290508021</int>
      <int>290508018</int>
      <int>290508019</int>
    </gift_list>
  </mzm.gsp.luckystar.confbean.SLuckyStarGiftCfg>
  <mzm.gsp.luckystar.confbean.SLuckyStarGiftCfg recommend_user_group_id="2315">
    <gift_list>
      <int>290502315</int>
    </gift_list>
  </mzm.gsp.luckystar.confbean.SLuckyStarGiftCfg>
  <mzm.gsp.luckystar.confbean.SLuckyStarGiftCfg recommend_user_group_id="8002">
    <gift_list>
      <int>290508015</int>
      <int>290508014</int>
      <int>290508013</int>
      <int>290508012</int>
      <int>290508016</int>
      <int>290508017</int>
    </gift_list>
  </mzm.gsp.luckystar.confbean.SLuckyStarGiftCfg>
  <mzm.gsp.luckystar.confbean.SLuckyStarGiftCfg recommend_user_group_id="2312">
    <gift_list>
      <int>290502312</int>
    </gift_list>
  </mzm.gsp.luckystar.confbean.SLuckyStarGiftCfg>
  <mzm.gsp.luckystar.confbean.SLuckyStarGiftCfg recommend_user_group_id="8001">
    <gift_list>
      <int>290508007</int>
      <int>290508006</int>
      <int>290508011</int>
      <int>290508010</int>
      <int>290508009</int>
      <int>290508008</int>
    </gift_list>
  </mzm.gsp.luckystar.confbean.SLuckyStarGiftCfg>
  <mzm.gsp.luckystar.confbean.SLuckyStarGiftCfg recommend_user_group_id="2313">
    <gift_list>
      <int>290502313</int>
    </gift_list>
  </mzm.gsp.luckystar.confbean.SLuckyStarGiftCfg>
  <mzm.gsp.luckystar.confbean.SLuckyStarGiftCfg recommend_user_group_id="8000">
    <gift_list>
      <int>290508005</int>
      <int>290508004</int>
      <int>290508003</int>
      <int>290508002</int>
      <int>290508001</int>
      <int>290508000</int>
    </gift_list>
  </mzm.gsp.luckystar.confbean.SLuckyStarGiftCfg>
  <mzm.gsp.luckystar.confbean.SLuckyStarGiftCfg recommend_user_group_id="2318">
    <gift_list>
      <int>290502318</int>
    </gift_list>
  </mzm.gsp.luckystar.confbean.SLuckyStarGiftCfg>
  <mzm.gsp.luckystar.confbean.SLuckyStarGiftCfg recommend_user_group_id="8007">
    <gift_list>
      <int>290508044</int>
      <int>290508047</int>
      <int>290508046</int>
      <int>290508045</int>
      <int>290508042</int>
      <int>290508043</int>
    </gift_list>
  </mzm.gsp.luckystar.confbean.SLuckyStarGiftCfg>
  <mzm.gsp.luckystar.confbean.SLuckyStarGiftCfg recommend_user_group_id="2319">
    <gift_list>
      <int>290502319</int>
    </gift_list>
  </mzm.gsp.luckystar.confbean.SLuckyStarGiftCfg>
  <mzm.gsp.luckystar.confbean.SLuckyStarGiftCfg recommend_user_group_id="8006">
    <gift_list>
      <int>290508038</int>
      <int>290508040</int>
      <int>290508039</int>
      <int>290508041</int>
      <int>290508036</int>
      <int>290508037</int>
    </gift_list>
  </mzm.gsp.luckystar.confbean.SLuckyStarGiftCfg>
  <mzm.gsp.luckystar.confbean.SLuckyStarGiftCfg recommend_user_group_id="2316">
    <gift_list>
      <int>290502316</int>
    </gift_list>
  </mzm.gsp.luckystar.confbean.SLuckyStarGiftCfg>
  <mzm.gsp.luckystar.confbean.SLuckyStarGiftCfg recommend_user_group_id="8005">
    <gift_list>
      <int>290508032</int>
      <int>290508034</int>
      <int>290508033</int>
      <int>290508035</int>
      <int>290508030</int>
      <int>290508031</int>
    </gift_list>
  </mzm.gsp.luckystar.confbean.SLuckyStarGiftCfg>
  <mzm.gsp.luckystar.confbean.SLuckyStarGiftCfg recommend_user_group_id="2317">
    <gift_list>
      <int>290502317</int>
    </gift_list>
  </mzm.gsp.luckystar.confbean.SLuckyStarGiftCfg>
  <mzm.gsp.luckystar.confbean.SLuckyStarGiftCfg recommend_user_group_id="8004">
    <gift_list>
      <int>290508028</int>
      <int>290508029</int>
      <int>290508026</int>
      <int>290508027</int>
      <int>290508024</int>
      <int>290508025</int>
    </gift_list>
  </mzm.gsp.luckystar.confbean.SLuckyStarGiftCfg>
  <mzm.gsp.luckystar.confbean.SLuckyStarGiftCfg recommend_user_group_id="2320">
    <gift_list>
      <int>290502320</int>
    </gift_list>
  </mzm.gsp.luckystar.confbean.SLuckyStarGiftCfg>
  <mzm.gsp.luckystar.confbean.SLuckyStarGiftCfg recommend_user_group_id="2604">
    <gift_list>
      <int>290502604</int>
    </gift_list>
  </mzm.gsp.luckystar.confbean.SLuckyStarGiftCfg>
  <mzm.gsp.luckystar.confbean.SLuckyStarGiftCfg recommend_user_group_id="2605">
    <gift_list>
      <int>290502605</int>
    </gift_list>
  </mzm.gsp.luckystar.confbean.SLuckyStarGiftCfg>
  <mzm.gsp.luckystar.confbean.SLuckyStarGiftCfg recommend_user_group_id="2602">
    <gift_list>
      <int>290502602</int>
    </gift_list>
  </mzm.gsp.luckystar.confbean.SLuckyStarGiftCfg>
  <mzm.gsp.luckystar.confbean.SLuckyStarGiftCfg recommend_user_group_id="2603">
    <gift_list>
      <int>290502603</int>
    </gift_list>
  </mzm.gsp.luckystar.confbean.SLuckyStarGiftCfg>
  <mzm.gsp.luckystar.confbean.SLuckyStarGiftCfg recommend_user_group_id="2601">
    <gift_list>
      <int>290502601</int>
    </gift_list>
  </mzm.gsp.luckystar.confbean.SLuckyStarGiftCfg>
  <mzm.gsp.luckystar.confbean.SLuckyStarGiftCfg recommend_user_group_id="2103">
    <gift_list>
      <int>290502103</int>
    </gift_list>
  </mzm.gsp.luckystar.confbean.SLuckyStarGiftCfg>
  <mzm.gsp.luckystar.confbean.SLuckyStarGiftCfg recommend_user_group_id="2102">
    <gift_list>
      <int>290502102</int>
    </gift_list>
  </mzm.gsp.luckystar.confbean.SLuckyStarGiftCfg>
  <mzm.gsp.luckystar.confbean.SLuckyStarGiftCfg recommend_user_group_id="2101">
    <gift_list>
      <int>290502101</int>
    </gift_list>
  </mzm.gsp.luckystar.confbean.SLuckyStarGiftCfg>
  <mzm.gsp.luckystar.confbean.SLuckyStarGiftCfg recommend_user_group_id="2816">
    <gift_list>
      <int>290502816</int>
    </gift_list>
  </mzm.gsp.luckystar.confbean.SLuckyStarGiftCfg>
  <mzm.gsp.luckystar.confbean.SLuckyStarGiftCfg recommend_user_group_id="2107">
    <gift_list>
      <int>290502107</int>
    </gift_list>
  </mzm.gsp.luckystar.confbean.SLuckyStarGiftCfg>
  <mzm.gsp.luckystar.confbean.SLuckyStarGiftCfg recommend_user_group_id="2106">
    <gift_list>
      <int>290502106</int>
    </gift_list>
  </mzm.gsp.luckystar.confbean.SLuckyStarGiftCfg>
  <mzm.gsp.luckystar.confbean.SLuckyStarGiftCfg recommend_user_group_id="2105">
    <gift_list>
      <int>290502105</int>
    </gift_list>
  </mzm.gsp.luckystar.confbean.SLuckyStarGiftCfg>
  <mzm.gsp.luckystar.confbean.SLuckyStarGiftCfg recommend_user_group_id="2104">
    <gift_list>
      <int>290502104</int>
    </gift_list>
  </mzm.gsp.luckystar.confbean.SLuckyStarGiftCfg>
  <mzm.gsp.luckystar.confbean.SLuckyStarGiftCfg recommend_user_group_id="2108">
    <gift_list>
      <int>290502108</int>
    </gift_list>
  </mzm.gsp.luckystar.confbean.SLuckyStarGiftCfg>
  <mzm.gsp.luckystar.confbean.SLuckyStarGiftCfg recommend_user_group_id="2404">
    <gift_list>
      <int>290502404</int>
    </gift_list>
  </mzm.gsp.luckystar.confbean.SLuckyStarGiftCfg>
  <mzm.gsp.luckystar.confbean.SLuckyStarGiftCfg recommend_user_group_id="2405">
    <gift_list>
      <int>290502405</int>
    </gift_list>
  </mzm.gsp.luckystar.confbean.SLuckyStarGiftCfg>
  <mzm.gsp.luckystar.confbean.SLuckyStarGiftCfg recommend_user_group_id="2406">
    <gift_list>
      <int>290502406</int>
    </gift_list>
  </mzm.gsp.luckystar.confbean.SLuckyStarGiftCfg>
  <mzm.gsp.luckystar.confbean.SLuckyStarGiftCfg recommend_user_group_id="2407">
    <gift_list>
      <int>290502407</int>
    </gift_list>
  </mzm.gsp.luckystar.confbean.SLuckyStarGiftCfg>
  <mzm.gsp.luckystar.confbean.SLuckyStarGiftCfg recommend_user_group_id="2401">
    <gift_list>
      <int>290502401</int>
    </gift_list>
  </mzm.gsp.luckystar.confbean.SLuckyStarGiftCfg>
  <mzm.gsp.luckystar.confbean.SLuckyStarGiftCfg recommend_user_group_id="2402">
    <gift_list>
      <int>290502402</int>
    </gift_list>
  </mzm.gsp.luckystar.confbean.SLuckyStarGiftCfg>
  <mzm.gsp.luckystar.confbean.SLuckyStarGiftCfg recommend_user_group_id="2403">
    <gift_list>
      <int>290502403</int>
    </gift_list>
  </mzm.gsp.luckystar.confbean.SLuckyStarGiftCfg>
  <mzm.gsp.luckystar.confbean.SLuckyStarGiftCfg recommend_user_group_id="2412">
    <gift_list>
      <int>290502412</int>
    </gift_list>
  </mzm.gsp.luckystar.confbean.SLuckyStarGiftCfg>
  <mzm.gsp.luckystar.confbean.SLuckyStarGiftCfg recommend_user_group_id="2413">
    <gift_list>
      <int>290502413</int>
    </gift_list>
  </mzm.gsp.luckystar.confbean.SLuckyStarGiftCfg>
  <mzm.gsp.luckystar.confbean.SLuckyStarGiftCfg recommend_user_group_id="2414">
    <gift_list>
      <int>290502414</int>
    </gift_list>
  </mzm.gsp.luckystar.confbean.SLuckyStarGiftCfg>
  <mzm.gsp.luckystar.confbean.SLuckyStarGiftCfg recommend_user_group_id="2415">
    <gift_list>
      <int>290502415</int>
    </gift_list>
  </mzm.gsp.luckystar.confbean.SLuckyStarGiftCfg>
  <mzm.gsp.luckystar.confbean.SLuckyStarGiftCfg recommend_user_group_id="2408">
    <gift_list>
      <int>290502408</int>
    </gift_list>
  </mzm.gsp.luckystar.confbean.SLuckyStarGiftCfg>
  <mzm.gsp.luckystar.confbean.SLuckyStarGiftCfg recommend_user_group_id="2409">
    <gift_list>
      <int>290502409</int>
    </gift_list>
  </mzm.gsp.luckystar.confbean.SLuckyStarGiftCfg>
  <mzm.gsp.luckystar.confbean.SLuckyStarGiftCfg recommend_user_group_id="2410">
    <gift_list>
      <int>290502410</int>
    </gift_list>
  </mzm.gsp.luckystar.confbean.SLuckyStarGiftCfg>
  <mzm.gsp.luckystar.confbean.SLuckyStarGiftCfg recommend_user_group_id="2411">
    <gift_list>
      <int>290502411</int>
    </gift_list>
  </mzm.gsp.luckystar.confbean.SLuckyStarGiftCfg>
  <mzm.gsp.luckystar.confbean.SLuckyStarGiftCfg recommend_user_group_id="2421">
    <gift_list>
      <int>290502421</int>
    </gift_list>
  </mzm.gsp.luckystar.confbean.SLuckyStarGiftCfg>
  <mzm.gsp.luckystar.confbean.SLuckyStarGiftCfg recommend_user_group_id="2420">
    <gift_list>
      <int>290502420</int>
    </gift_list>
  </mzm.gsp.luckystar.confbean.SLuckyStarGiftCfg>
  <mzm.gsp.luckystar.confbean.SLuckyStarGiftCfg recommend_user_group_id="2423">
    <gift_list>
      <int>290502423</int>
    </gift_list>
  </mzm.gsp.luckystar.confbean.SLuckyStarGiftCfg>
  <mzm.gsp.luckystar.confbean.SLuckyStarGiftCfg recommend_user_group_id="2422">
    <gift_list>
      <int>290502422</int>
    </gift_list>
  </mzm.gsp.luckystar.confbean.SLuckyStarGiftCfg>
  <mzm.gsp.luckystar.confbean.SLuckyStarGiftCfg recommend_user_group_id="2417">
    <gift_list>
      <int>290502417</int>
    </gift_list>
  </mzm.gsp.luckystar.confbean.SLuckyStarGiftCfg>
  <mzm.gsp.luckystar.confbean.SLuckyStarGiftCfg recommend_user_group_id="2416">
    <gift_list>
      <int>290502416</int>
    </gift_list>
  </mzm.gsp.luckystar.confbean.SLuckyStarGiftCfg>
  <mzm.gsp.luckystar.confbean.SLuckyStarGiftCfg recommend_user_group_id="2419">
    <gift_list>
      <int>290502419</int>
    </gift_list>
  </mzm.gsp.luckystar.confbean.SLuckyStarGiftCfg>
  <mzm.gsp.luckystar.confbean.SLuckyStarGiftCfg recommend_user_group_id="2418">
    <gift_list>
      <int>290502418</int>
    </gift_list>
  </mzm.gsp.luckystar.confbean.SLuckyStarGiftCfg>
  <mzm.gsp.luckystar.confbean.SLuckyStarGiftCfg recommend_user_group_id="2429">
    <gift_list>
      <int>290502429</int>
    </gift_list>
  </mzm.gsp.luckystar.confbean.SLuckyStarGiftCfg>
  <mzm.gsp.luckystar.confbean.SLuckyStarGiftCfg recommend_user_group_id="2428">
    <gift_list>
      <int>290502428</int>
    </gift_list>
  </mzm.gsp.luckystar.confbean.SLuckyStarGiftCfg>
  <mzm.gsp.luckystar.confbean.SLuckyStarGiftCfg recommend_user_group_id="2430">
    <gift_list>
      <int>290502430</int>
    </gift_list>
  </mzm.gsp.luckystar.confbean.SLuckyStarGiftCfg>
  <mzm.gsp.luckystar.confbean.SLuckyStarGiftCfg recommend_user_group_id="2425">
    <gift_list>
      <int>290502425</int>
    </gift_list>
  </mzm.gsp.luckystar.confbean.SLuckyStarGiftCfg>
  <mzm.gsp.luckystar.confbean.SLuckyStarGiftCfg recommend_user_group_id="2424">
    <gift_list>
      <int>290502424</int>
    </gift_list>
  </mzm.gsp.luckystar.confbean.SLuckyStarGiftCfg>
  <mzm.gsp.luckystar.confbean.SLuckyStarGiftCfg recommend_user_group_id="2427">
    <gift_list>
      <int>290502427</int>
    </gift_list>
  </mzm.gsp.luckystar.confbean.SLuckyStarGiftCfg>
  <mzm.gsp.luckystar.confbean.SLuckyStarGiftCfg recommend_user_group_id="2426">
    <gift_list>
      <int>290502426</int>
    </gift_list>
  </mzm.gsp.luckystar.confbean.SLuckyStarGiftCfg>
</data>
